mcping_nonebot2-1.0.9.dist-info/licenses/LICENSE
nonebot_plugin_mcping/__init__.py
nonebot_plugin_mcping/config.py
mcping_nonebot2-1.0.9.dist-info/METADATA
mcping_nonebot2-1.0.9.dist-info/WHEEL
mcping_nonebot2-1.0.9.dist-info/top_level.txt
mcping_nonebot2-1.0.9.dist-info/RECORD
