Metadata-Version: 2.4
Name: mcping_nonebot2
Version: 1.0.9
Summary: mcping with nonebot2
Home-page: https://github.com/Coloryr/mcping_nonebot2
Author: coloryr
Author-email: 402067010@qq.com
Classifier: Programming Language :: Python :: 3
Classifier: License :: OSI Approved :: MIT License
Classifier: Operating System :: OS Independent
Requires-Python: >=3
License-File: LICENSE
Requires-Dist: nonebot2
Requires-Dist: nonebot-adapter-qq
Dynamic: author
Dynamic: author-email
Dynamic: classifier
Dynamic: description
Dynamic: description-content-type
Dynamic: home-page
Dynamic: license-file
Dynamic: requires-dist
Dynamic: requires-python
Dynamic: summary
